{
  "project_info": {
    "project_number": "834952308922",
    "project_id": "geoapp-fb",
    "storage_bucket": "geoapp-fb.firebasestorage.app"
  },
  "client": [
    {
      "client_info": {
        "mobilesdk_app_id": "1:834952308922:android:3112403ffcbb21db03fa83",
        "android_client_info": {
          "package_name": "com.coldenjohnson.geoapp"
        }
      },
      "oauth_client": [],
      "api_key": [
        {
          "current_key": "AIzaSyD1iY87iPXEjwNPUpcfmB8IuNSmjp_4S84"
        }
      ],
      "services": {
        "appinvite_service": {
          "other_platform_oauth_client": []
        }
      }
    },
    {
      "client_info": {
        "mobilesdk_app_id": "1:834952308922:android:e8ae594f350ab35303fa83",
        "android_client_info": {
          "package_name": "com.coldenjohnson.geode"
        }
      },
      "oauth_client": [],
      "api_key": [
        {
          "current_key": "AIzaSyD1iY87iPXEjwNPUpcfmB8IuNSmjp_4S84"
        }
      ],
      "services": {
        "appinvite_service": {
          "other_platform_oauth_client": []
        }
      }
    }
  ],
  "configuration_version": "1"
}